Workbook

Sheet Resumo
A1: Relatório de disparos Blip: setembro/2026
A2: Fatura 886000007603 e campanhas de 01 a 30/09/2026
A4: Indicador | B4: Valor | C4: Observação
A5: Total a pagar da fatura | B5: =Fatura!B10 -> 70032.92 | C5: Conciliado com os itens da fatura. Vencimento 25/11/2026
A6: Plano contratado | B6: =Fatura!B5 -> 16479.95 | C6: Custo fixo
A7: Canal WhatsApp (mensagens) | B7: =Fatura!B6 -> 52823.97 | C7: Consumo; tarifas confirmadas (R$ 0,09 Utilidade, R$ 0,54 Marketing Lite)
A8: Número adicional e contratações adicionais | B8: =Fatura!B7+Fatura!B8 -> 729 | C8: Custos fixos e adicionais
A9: Campanhas no período | B9: ='Resultados por ação'!B19 -> 176 | C9: Aba Resultados por ação
A10: Mensagens enviadas | B10: ='Resultados por ação'!C19 -> 329009
A11: Mensagens entregues | B11: ='Resultados por ação'!D19 -> 239242
A12: Custo das campanhas (mensagens) | B12: ='Resultados por ação'!E19 -> 52604.28 | C12: Entregues x tarifa da fatura
A13: Receita atribuída | B13: ='Resultados por ação'!F19 -> 887405 | C13: Valor de vendas informado por ação
A14: ROAS (receita / custo das campanhas) | B14: ='Resultados por ação'!G19 -> 16.869445
A15: ROAS sobre o total da fatura | B15: ='Resultados por ação'!F19/Fatura!B10 -> 12.671255 | C15: Inclui plano e adicionais no custo
A17: Não disponível nas fontes | B17: Situação | C17: Detalhe
A18: Quantidade de vendas | B18: Não informada | C18: Só há valor de vendas por ação
A19: Ações sem vendas | B19: 3 ações | C19: Governança Ágil, Conselho Empresarial da Saúde (Workshop) e Apoio Marketing: R$ 0, ROAS 0x

Sheet Fatura
A1: Fatura 886000007603: composição e conciliação (setembro/2026)
A4: 1. Composição da fatura | B4: Valor (R$) | C4: Observação
A5: Plano Contratado (BUSINESSMAU) | B5: 16479.95 | C5: Custo fixo
A6: Canal WhatsApp | B6: 52823.97 | C6: Consumo de mensagens (seção 2)
A7: Número Adicional | B7: 500 | C7: Custo fixo
A8: Contratações Adicionais | B8: 229 | C8: Cobrança adicional
A9: Total da fatura | B9: =SUM(B5:B8) -> 70032.92
A10: Total a pagar (boleto) | B10: 70032.92 | C10: Boleto nº 0010058580, vencimento 25/11/2026
A11: Diferença | B11: =B9-B10 -> 0 | C11: =IF(ROUND(B11,2)=0,"Conciliado","Divergência") -> Conciliado
A12: A fatura não traz taxas separadas.
A14: 2. Canal WhatsApp por categoria | B14: Mensagens entregues | C14: Tarifa (R$) | D14: Valor (R$) | E14: Situação
A15: Utilidade | B15: 170749 | C15: 0.09 | D15: =B15*C15 -> 15367.41
A16: Marketing Lite | B16: 69364 | C16: 0.54 | D16: =B16*C16 -> 37456.56
A17: Total | B17: =SUM(B15:B16) -> 240113 | D17: =SUM(D15:D16) -> 52823.97
A18: Diferença vs Canal WhatsApp da fatura | D18: =D17-B6 -> 0 | E18: =IF(ROUND(D18,2)=0,"Conciliado: tarifas confirmadas","Divergência") -> Conciliado: tarifas confirmadas
A20: 3. Custo por campanha vs fatura | B20: Mensagens entregues | C20: Custo (R$) | D20: Observação
A21: Utilidade (campanhas) | B21: 170192 | C21: 15317.28
A22: Marketing Lite (campanhas) | B22: 69050 | C22: 37287
A23: Custo das campanhas | B23: =SUM(B21:B22) -> 239242 | C23: =SUM(C21:C22) -> 52604.28 | D23: =IF(ROUND(C23-'Resultados por ação'!E19,2)=0,"Confere com a aba Resultados por ação","Divergência") -> Confere com a aba Resultados por ação
A24: Consumo cobrado sem campanha no relatório | B24: =B17-B23 -> 871 | C24: =D17-C23 -> 219.69 | D24: Diferença de 0,4% entre o consumo cobrado e o relatório de campanhas
A25: Custos fixos e adicionais (plano, número, contratações) | C25: =B5+B7+B8 -> 17208.95 | D25: Não se atribuem a campanhas
A26: Total (campanhas + diferença + fixos) | C26: =C23+C24+C25 -> 70032.92
A27: Diferença vs total a pagar | C27: =C26-B10 -> 0 | D27: =IF(ROUND(C27,2)=0,"Conciliado","Divergência") -> Conciliado

Sheet Resultados por ação
A1: Resultados e ROAS por ação (setembro/2026)
A2: Receita = vendas realizadas informadas por ação no consolidado de disparos. Custo = entregues x tarifa da fatura (R$ 0,09 Utilidade; R$ 0,54 Marketing Lite). ROAS = receita / custo de mensagens.
A4: Ação / evento | B4: Campanhas | C4: Enviadas | D4: Entregues | E4: Custo (R$) | F4: Receita (R$) | G4: ROAS | H4: Situação
A5: Q&A - Carreira de Conselho | B5: 17 | C5: 36994 | D5: 28194 | E5: 2537.46 | F5: 80495 | G5: =IFERROR(F5/E5,"") -> 31.722668 | H5: Receita informada
A6: Base de Deals abertos | B6: 31 | C6: 47919 | D6: 32999 | E6: 16148.61 | F6: 286558 | G6: =IFERROR(F6/E6,"") -> 17.745057 | H6: Receita informada
A7: Q&A - Conselho Empresarial da Saúde | B7: 5 | C7: 11959 | D7: 9580 | E7: 862.2 | F7: 16397 | G7: =IFERROR(F7/E7,"") -> 19.017629 | H7: Receita informada
A8: Workshop - Pré Conselho | B8: 14 | C8: 23986 | D8: 18419 | E8: 1866.96 | F8: 102363 | G8: =IFERROR(F8/E8,"") -> 54.828705 | H8: Receita informada
A9: Workshop - Governança Ágil | B9: 13 | C9: 23168 | D9: 14903 | E9: 1341.27 | F9: 0 | G9: =IFERROR(F9/E9,"") -> 0 | H9: Sem vendas
A10: Workshop - Advisor Program | B10: 60 | C10: 119538 | D10: 87045 | E10: 10528.65 | F10: 37442 | G10: =IFERROR(F10/E10,"") -> 3.5562014 | H10: Receita informada
A11: Workshop - Conselho Empresarial da Saúde | B11: 6 | C11: 11363 | D11: 7521 | E11: 2828.79 | F11: 0 | G11: =IFERROR(F11/E11,"") -> 0 | H11: Sem vendas
A12: Workshop Panorama do Mercado de Conselheiros | B12: 15 | C12: 27905 | D12: 20313 | E12: 7931.52 | F12: 27387 | G12: =IFERROR(F12/E12,"") -> 3.4529321 | H12: Receita informada
A13: Apoio Marketing | B13: 1 | C13: 2914 | D13: 2022 | E13: 1091.88 | F13: 0 | G13: =IFERROR(F13/E13,"") -> 0 | H13: Sem vendas
A14: WORKSHOP BOARD SELECT: Onde os Conselheiros se Encontram para Evoluir | B14: 5 | C14: 7173 | D14: 5125 | E14: 2767.5 | F14: 27350 | G14: =IFERROR(F14/E14,"") -> 9.8825655 | H14: Receita informada
A15: Board Sprint | B15: 5 | C15: 8028 | D15: 6661 | E15: 1211.04 | F15: 47973 | G15: =IFERROR(F15/E15,"") -> 39.61306 | H15: Receita informada
A16: Consumidor 1309 | B16: 2 | C16: 2342 | D16: 1870 | E16: 1009.8 | F16: 48000 | G16: =IFERROR(F16/E16,"") -> 47.534165 | H16: Receita informada
... A18: Coautoria 0709 | B18: 1 | C18: 5311 | D18: 4266 | E18: 2303.64 | F18: 190758 | G18: =IFERROR(F18/E18,"") -> 82.807209 | H18: Receita informada
A19: TOTAL | B19: =SUM(B5:B18) -> 176 | C19: =SUM(C5:C18) -> 329009 | D19: =SUM(D5:D18) -> 239242 | E19: =SUM(E5:E18) -> 52604.28 | F19: =SUM(F5:F18) -> 887405 | G19: =IFERROR(F19/E19,"") -> 16.869445
A21: Ações marcadas "Sem vendas" não tiveram vendas (R$ 0, ROAS 0x). Número e valor de vendas por campanha não constam na fonte.
